TrajectoryNet/__init__.py
TrajectoryNet/dataset.py
TrajectoryNet/eval.py
TrajectoryNet/eval_utils.py
TrajectoryNet/main.py
TrajectoryNet/parse.py
TrajectoryNet/train_growth.py
TrajectoryNet/train_misc.py
TrajectoryNet/version.py
TrajectoryNet/lib/__init__.py
TrajectoryNet/lib/growth_net.py
TrajectoryNet/lib/spectral_norm.py
TrajectoryNet/lib/utils.py
TrajectoryNet/lib/visualize_flow.py
TrajectoryNet/lib/viz_scrna.py
TrajectoryNet/lib/layers/__init__.py
TrajectoryNet/lib/layers/cnf.py
TrajectoryNet/lib/layers/container.py
TrajectoryNet/lib/layers/coupling.py
TrajectoryNet/lib/layers/elemwise.py
TrajectoryNet/lib/layers/glow.py
TrajectoryNet/lib/layers/norm_flows.py
TrajectoryNet/lib/layers/normalization.py
TrajectoryNet/lib/layers/odefunc.py
TrajectoryNet/lib/layers/resnet.py
TrajectoryNet/lib/layers/squeeze.py
TrajectoryNet/lib/layers/diffeq_layers/__init__.py
TrajectoryNet/lib/layers/diffeq_layers/basic.py
TrajectoryNet/lib/layers/diffeq_layers/container.py
TrajectoryNet/lib/layers/diffeq_layers/resnet.py
TrajectoryNet/lib/layers/diffeq_layers/wrappers.py
TrajectoryNet/lib/layers/wrappers/__init__.py
TrajectoryNet/lib/layers/wrappers/cnf_regularization.py
TrajectoryNet/optimal_transport/MMD.py
TrajectoryNet/optimal_transport/__init__.py
TrajectoryNet/optimal_transport/emd.py
TrajectoryNet/optimal_transport/plot_UOT_1D.py
TrajectoryNet/optimal_transport/sinkhorn_knopp_unbalanced.py
TrajectoryNet/optimal_transport/train_growth.py
TrajectoryNet-0.2.4.dist-info/LICENSE
TrajectoryNet-0.2.4.dist-info/METADATA
TrajectoryNet-0.2.4.dist-info/WHEEL
TrajectoryNet-0.2.4.dist-info/top_level.txt
TrajectoryNet-0.2.4.dist-info/RECORD
