Metadata-Version: 2.1
Name: TrajectoryNet
Version: 0.2.4
Summary: A neural ode solution for imputing trajectories between pointclouds.
Home-page: https://github.com/KrishnaswamyLab/TrajectoryNet
Author: Alexander Tong
Author-email: alexandertongdev@gmail.com
License: MIT
Platform: UNKNOWN
License-File: LICENSE
Requires-Dist: argparse
Requires-Dist: matplotlib (>=3.2.1)
Requires-Dist: numpy (>=1.18.4)
Requires-Dist: POT (>=0.7.0)
Requires-Dist: scanpy
Requires-Dist: scikit-learn (>=0.23.1)
Requires-Dist: scipy (>=1.4.1)
Requires-Dist: torch (>=1.5.0)
Requires-Dist: torchdiffeq (==0.0.1)
